blin/__init__.py
blin-0.2.1.dist-info/METADATA
blin-0.2.1.dist-info/WHEEL
blin-0.2.1.dist-info/license.txt
blin-0.2.1.dist-info/top_level.txt
blin-0.2.1.dist-info/RECORD
