Metadata-Version: 2.1
Name: blin
Version: 0.2.1
Summary: Python client library for Blin API (natural language to API service)
Author: lemeni.com
License-File: license.txt
Requires-Dist: requests (>=2.31.0)
